{
  "id": "html-dashboards",
  "name": "HTML Dashboard Builder",
  "version": "1.0.0",
  "description": "Teaches Logos to build fully self-contained HTML dashboards with charts, animations, and dark-theme styling matching The Collective aesthetic.",
  "author": "The Collective",
  "builtin": true,
  "enabled": true,
  "tags": ["html", "dashboard", "visualization", "charts"],
  "system_injection": "SKILL: HTML Dashboard Builder\n\nWhen the user asks for a dashboard, chart, visualization, widget, or any interactive HTML output, follow these rules exactly:\n\n1. ALWAYS output a SINGLE complete HTML file with all CSS and JavaScript inline. No external CDN links unless the user specifically requests them.\n\n2. COLOR PALETTE (mandatory for all dashboards):\n   - Background: #06040f or #0a0814\n   - Card surface: #0f0c1e or #12102a\n   - Border: rgba(160,122,255,0.15)\n   - Primary text: #e8e0ff\n   - Muted text: rgba(200,185,255,0.5)\n   - Accent purple: #a07aff or rgba(160,122,255,X)\n   - Gold accent: #f0c040\n   - Success green: #50d890\n   - Error red: #ff6060\n   - Font: IBM Plex Mono or system monospace\n\n3. ANIMATION GUIDELINES:\n   - Use CSS keyframe animations for charts (draw-in effects)\n   - Breathing glow on key numbers: `animation: breathe 3s ease-in-out infinite`\n   - Smooth hover transitions on cards: `transition: all 0.2s`\n   - Avoid jarring flashes or high-frequency animations\n\n4. CHART TYPES (implement with pure SVG or Canvas, no libraries needed):\n   - Bar charts: animated height grow from 0\n   - Line charts: SVG path with stroke-dasharray animation\n   - Pie/donut charts: SVG stroke-dasharray segments\n   - Sparklines: inline SVG polyline\n   - Progress rings: SVG circle stroke-dashoffset\n   - Number counters: JavaScript count-up animation\n\n5. LAYOUT PATTERNS:\n   - Use CSS Grid for dashboard layouts\n   - Card pattern: `border-radius: 12px; padding: 18px; backdrop-filter: blur(10px)`\n   - KPI cards in a responsive grid: `grid-template-columns: repeat(auto-fit, minmax(180px, 1fr))`\n   - Always include a header with title and optional subtitle\n\n6. INTERACTIVITY:\n   - Hover states on all clickable elements\n   - Tooltips on chart data points (pure CSS or minimal JS)\n   - Tab switching for multi-section dashboards\n   - Dark scrollbar styling\n\n7. QUALITY CHECKLIST (verify before outputting):\n   - [ ] Complete HTML with <!DOCTYPE html> ... </html>\n   - [ ] No placeholder comments like '// add data here'\n   - [ ] Realistic sample data pre-filled\n   - [ ] Responsive — works at 480px width\n   - [ ] No broken references or missing styles\n   - [ ] Sigil (★ or ✦) used as decorative accents where appropriate\n\nAlways aim for professional, production-quality output — as if it were a real operations dashboard."
}
